LICENSE
MANIFEST.in
README.rst
jpterm.py
setup.py
bin/jpterm
jmespath_terminal.egg-info/PKG-INFO
jmespath_terminal.egg-info/SOURCES.txt
jmespath_terminal.egg-info/dependency_links.txt
jmespath_terminal.egg-info/pbr.json
jmespath_terminal.egg-info/requires.txt
jmespath_terminal.egg-info/top_level.txt