Metadata-Version: 1.1
Name: jmespath-terminal
Version: 0.2.0
Summary: JMESPath Terminal
Home-page: https://github.com/jmespath/jmespath.terminal
Author: James Saryerwinnie
Author-email: js@jamesls.com
License: UNKNOWN
Platform: UNKNOWN
Classifier: Development Status :: 4 - Beta
Classifier: Intended Audience :: Developers
Classifier: Natural Language :: English
Classifier: License :: OSI Approved :: Apache Software License
Classifier: Programming Language :: Python
Classifier: Programming Language :: Python :: 2.6
Classifier: Programming Language :: Python :: 2.7
Classifier: Programming Language :: Python :: 3
Classifier: Programming Language :: Python :: 3.3
